universal_notifications/__init__.py
universal_notifications/admin.py
universal_notifications/api.py
universal_notifications/api_urls.py
universal_notifications/docs.py
universal_notifications/models.py
universal_notifications/notifications.py
universal_notifications/serializers.py
universal_notifications/signals.py
universal_notifications/tasks.py
universal_notifications/urls.py
universal_notifications/backends/__init__.py
universal_notifications/backends/websockets.py
universal_notifications/backends/emails/__init__.py
universal_notifications/backends/emails/models.py
universal_notifications/backends/emails/urls.py
universal_notifications/backends/emails/views.py
universal_notifications/backends/push/__init__.py
universal_notifications/backends/push/apns.py
universal_notifications/backends/push/fcm.py
universal_notifications/backends/push/gcm.py
universal_notifications/backends/push/utils.py
universal_notifications/backends/sms/__init__.py
universal_notifications/backends/sms/abstract.py
universal_notifications/backends/sms/base.py
universal_notifications/backends/sms/signals.py
universal_notifications/backends/sms/utils.py
universal_notifications/backends/sms/engines/__init__.py
universal_notifications/backends/sms/engines/amazonsns.py
universal_notifications/backends/sms/engines/twilio.py
universal_notifications/backends/twilio/__init__.py
universal_notifications/backends/twilio/api.py
universal_notifications/backends/twilio/fields.py
universal_notifications/management/__init__.py
universal_notifications/management/commands/__init__.py
universal_notifications/management/commands/check_twilio_proxy.py
universal_notifications/management/commands/parse_pending_sms.py
universal_notifications/management/commands/run_twilio_proxy.py
universal_notifications/migrations/0001_initial.py
universal_notifications/migrations/0002_device.py
universal_notifications/migrations/0003_auto_20170112_0609.py
universal_notifications/migrations/0004_auto_20170124_0731.py
universal_notifications-1.6.0.dist-info/LICENSE
universal_notifications-1.6.0.dist-info/METADATA
universal_notifications-1.6.0.dist-info/WHEEL
universal_notifications-1.6.0.dist-info/top_level.txt
universal_notifications-1.6.0.dist-info/RECORD
