Metadata-Version: 2.1
Name: universal-notifications
Version: 1.6.0
Summary: High-level framework for notifications
Home-page: https://github.com/HealthByRo/universal_notifications
Author: Pawel Krzyzaniak
Author-email: pawelk@ro.co
License: MIT
Classifier: Development Status :: 5 - Production/Stable
Classifier: Environment :: Web Environment
Classifier: Framework :: Django
Classifier: Intended Audience :: Developers
Classifier: Operating System :: OS Independent
Classifier: Programming Language :: Python
Classifier: Programming Language :: Python :: 3.6
Classifier: Programming Language :: Python :: 3.7
Classifier: Programming Language :: Python :: 3.8
Classifier: Programming Language :: Python :: 3.9
Classifier: Topic :: Internet :: WWW/HTTP
License-File: LICENSE
Requires-Dist: djangorestframework >=3.7
Requires-Dist: django-rest-swagger >=2.1.2
Requires-Dist: django-websocket-redis
Requires-Dist: redis
Requires-Dist: premailer >=3.1.0
Requires-Dist: six >=1.10.0
Requires-Dist: coreapi <3.0.0,>=2.3.1
Requires-Dist: django-push-notifications <1.5.0,>=1.4.1
Requires-Dist: pyfcm
Requires-Dist: phonenumbers >=7.7.3
Requires-Dist: twilio <8.0.0,>=6.0.0
Requires-Dist: boto3 <2.0.0,>1.4.0
